odoo/addons/fleet_vehicle_license_plate_alt/README.rst
odoo/addons/fleet_vehicle_license_plate_alt/__init__.py
odoo/addons/fleet_vehicle_license_plate_alt/__manifest__.py
odoo/addons/fleet_vehicle_license_plate_alt/models/__init__.py
odoo/addons/fleet_vehicle_license_plate_alt/models/fleet_vehicle.py
odoo/addons/fleet_vehicle_license_plate_alt/readme/CONTRIBUTORS.rst
odoo/addons/fleet_vehicle_license_plate_alt/readme/DESCRIPTION.rst
odoo/addons/fleet_vehicle_license_plate_alt/static/description/icon.png
odoo/addons/fleet_vehicle_license_plate_alt/static/description/index.html
odoo/addons/fleet_vehicle_license_plate_alt/tests/__init__.py
odoo/addons/fleet_vehicle_license_plate_alt/tests/test_vehicle_license_plate_alt.py
odoo/addons/fleet_vehicle_license_plate_alt/views/fleet_vehicle_views.xml
odoo12_addon_fleet_vehicle_license_plate_alt-12.0.1.0.0.dist-info/METADATA
odoo12_addon_fleet_vehicle_license_plate_alt-12.0.1.0.0.dist-info/WHEEL
odoo12_addon_fleet_vehicle_license_plate_alt-12.0.1.0.0.dist-info/top_level.txt
odoo12_addon_fleet_vehicle_license_plate_alt-12.0.1.0.0.dist-info/RECORD
