Metadata-Version: 2.1
Name: odoo12-addon-fleet-vehicle-license-plate-alt
Version: 12.0.1.0.0
Summary: Add a new field in the vehicle, to store an alternative license plate.
Home-page: https://github.com/OCA/fleet
Author: Druidoo, Odoo Community Association (OCA)
Author-email: support@odoo-community.org
License: AGPL-3
Platform: UNKNOWN
Classifier: Programming Language :: Python
Classifier: Framework :: Odoo
Classifier: License :: OSI Approved :: GNU Affero General Public License v3
Classifier: Development Status :: 5 - Production/Stable
Requires-Python: >=3.5
Requires-Dist: odoo (<12.1dev,>=12.0a)
